cookie_puppeteer/__init__.py
cookie_puppeteer/console.py
cookie_puppeteer-0.0.1.dist-info/LICENSE
cookie_puppeteer-0.0.1.dist-info/METADATA
cookie_puppeteer-0.0.1.dist-info/WHEEL
cookie_puppeteer-0.0.1.dist-info/entry_points.txt
cookie_puppeteer-0.0.1.dist-info/top_level.txt
cookie_puppeteer-0.0.1.dist-info/RECORD
