Metadata-Version: 2.1
Name: cookie-puppeteer
Version: 0.0.1
Summary: Retrieve cookies exported by Export cookie JSON File Puppeteer extension 
Home-page: https://github.com/Simatwa/cookie-puppeteer
Author: Smartwa
Author-email: simatwacaleb@proton.me
Maintainer: Smartwa
License: MIT
Project-URL: Bug Report, https://github.com/Simatwa/cookie-puppeteer/issues/new
Project-URL: Homepage, https://github.com/Simatwa/cookie-puppeteer
Project-URL: Source Code, https://github.com/Simatwa/cookie-puppeteer
Project-URL: Issue Tracker, https://github.com/Simatwa/cookie-puppeteer/issues
Project-URL: Download, https://github.com/Simatwa/cookie-puppeteer/releases
Project-URL: Documentation, https://github.com/Simatwa/cookie-puppeteer/blob/main/docs
Keywords: cookies,cookies-puppeteer
Classifier: License :: OSI Approved :: MIT License
Classifier: Intended Audience :: Developers
Classifier: Programming Language :: Python
Classifier: Topic :: Software Development :: Libraries :: Python Modules
Classifier: Programming Language :: Python :: 3 :: Only
Classifier: Programming Language :: Python :: 3.10
Classifier: Programming Language :: Python :: 3.11
Classifier: Programming Language :: Python :: 3.12
Requires-Python: >=3.10
License-File: LICENSE
